CHANGES.txt
LICENSE.txt
README.txt
bootstrap.py
buildout.cfg
setup.py
src/getpaid/__init__.py
src/getpaid.ogone.egg-info/PKG-INFO
src/getpaid.ogone.egg-info/SOURCES.txt
src/getpaid.ogone.egg-info/dependency_links.txt
src/getpaid.ogone.egg-info/namespace_packages.txt
src/getpaid.ogone.egg-info/not-zip-safe
src/getpaid.ogone.egg-info/requires.txt
src/getpaid.ogone.egg-info/top_level.txt
src/getpaid/ogone/README.txt
src/getpaid/ogone/__init__.py
src/getpaid/ogone/configure.zcml
src/getpaid/ogone/currencies.txt
src/getpaid/ogone/interfaces.py
src/getpaid/ogone/ogone.py
src/getpaid/ogone/overrides.zcml
src/getpaid/ogone/vocabulary.py
src/getpaid/ogone/vocabulary.zcml
src/getpaid/ogone/browser/__init__.py
src/getpaid/ogone/browser/check.py
src/getpaid/ogone/browser/checkout.py
src/getpaid/ogone/browser/configure.zcml
src/getpaid/ogone/browser/postProcess.py
src/getpaid/ogone/browser/templates/accepted.pt
src/getpaid/ogone/browser/templates/cancelled.pt
src/getpaid/ogone/browser/templates/checkout-review-pay.pt
src/getpaid/ogone/i18n/Makefile
src/getpaid/ogone/i18n/formulator_extract.py
src/getpaid/ogone/i18n/getpaid.ogone-fr.po
src/getpaid/ogone/i18n/getpaid.ogone.pot
src/getpaid/ogone/i18n/i18nextract
src/getpaid/ogone/i18n/metadata_extract.py
src/getpaid/ogone/tests/__init__.py
src/getpaid/ogone/tests/ogone.txt
src/getpaid/ogone/tests/test_ogone.py