Metadata-Version: 1.0
Name: getpaid.ogone
Version: 0.3
Summary: Get paid ogone payment processor functionality
Home-page: http://code.google.com/p/getpaid
Author: Getpaid Community
Author-email: getpaid-dev@googlegroups.com
License: ZPL2.1
Platform: UNKNOWN
Classifier: Framework :: Zope2
Classifier: Framework :: Zope3
Classifier: Framework :: Plone
